{
    "greeting": "Chao xìn",
    "name": "Nguyễn Dương Thư Kỳ ❤️",
    "greetingText": "- AKA Em bé của anh -",
    "wishText": "Chúc em bé sinh nhật thiệt là vui vẻ, hạnh phúc, hạnh phúc bên gia đình người thân và đặc biệt là bên anh, mong em lúc nào cũng xinh đẹp, lúc nào cũng tươi tắn khỏe khoắn. Chúc em trong tương lai sẽ đạt được những thứ em mong muốn, hơn nữa chúc em sẽ cùng anh làm được nhiều thứ hơn trong tương lai và cuối cùng tuổi mới thì anh mong em bé sẽ nghe lời anh hơn, cố gắng chăm sóc bản thân tốt hơn nè và cười nhiều hơn nheee <3",
    "imagePath": "img/embe.jpg",
    "text1": "Hôm nay là sinh nhật đầu tiên mà 2 đứa mình có nhau 🥰",
    "textInChatBox": "Happy Birthday Sweetie 🎂",
    "sendButtonLabel": "Send",
    "text2": "Hmm, anh cảm thấy vui khi được lần đầu tiên tổ chức sinh nhật cho bé",
    "text3": "Và không chỉ dừng ở đó",
    "text4": "Anh có 1 lời chúc dành cho em cực kì ",
    "text4Adjective": "ĐẶC BIỆT...",
    "text5Entry": "Bởi vì,",
    "text5Content": "em là em bé của anh",
    "smiley": ":3",
    "bigTextPart1": "cho",
    "bigTextPart2": "nên",
    "wishHeading": "Happy Birthday!",
    "outroText": "Hmm, đơn giản chỉ là những lời chúc hoiii, mong em bé thích <3",
    "replayText": "Click vào đây nếu em bé muốn xem lại.",
    "outroSmiley": ":)"
}